cluster_explorer/AnalyzeItemsets.py
cluster_explorer/ScoreMetrics.py
cluster_explorer/__init__.py
cluster_explorer/binning_methods.py
cluster_explorer/explainer.py
cluster_explorer/gFIM.py
cluster_explorer/utils.py
cluster_explorer-1.0.2.dist-info/LICENSE
cluster_explorer-1.0.2.dist-info/METADATA
cluster_explorer-1.0.2.dist-info/WHEEL
cluster_explorer-1.0.2.dist-info/top_level.txt
cluster_explorer-1.0.2.dist-info/RECORD
