Metadata-Version: 2.2
Name: cluster_explorer
Version: 1.0.2
Project-URL: Git, https://github.com/analysis-bots/cluster-explorer
License-File: LICENSE
Requires-Dist: wheel
Requires-Dist: pandas>=2.2.3
Requires-Dist: numpy>=2.1.3
Requires-Dist: scikit-learn>=1.6.0
Requires-Dist: optbinning>=0.20.1
Dynamic: description
Dynamic: description-content-type
Dynamic: project-url
Dynamic: requires-dist
